parse_vcf.py
test_parse_vcf.py
parse_vcf-0.2.8.dist-info/LICENSE.txt
parse_vcf-0.2.8.dist-info/METADATA
parse_vcf-0.2.8.dist-info/WHEEL
parse_vcf-0.2.8.dist-info/top_level.txt
parse_vcf-0.2.8.dist-info/RECORD
