Metadata-Version: 2.1
Name: parse-vcf
Version: 0.2.8
Summary: Variant Call Format parser and convenience methods
Home-page: https://github.com/david-a-parry/parse_vcf.py
Author: David A. Parry
Author-email: david.parry@igmm.ed.ac.uk
License: MIT
Download-URL: https://github.com/david-a-parry/parse_vcf.py/archive/0.2.8.tar.gz
Platform: UNKNOWN
Classifier: Programming Language :: Python :: 3
Classifier: Development Status :: 3 - Alpha
Classifier: Intended Audience :: Developers
Classifier: Intended Audience :: Science/Research
Classifier: License :: OSI Approved :: MIT License
Classifier: Topic :: Scientific/Engineering :: Bio-Informatics
Requires-Python: >=3
Requires-Dist: pysam
